splink_data_generation/estimate_splink.py
splink_data_generation/generate_data_exact.py
splink_data_generation/generate_data_random.py
splink_data_generation/log_likelihood.py
splink_data_generation/match_prob.py
splink_data_generation-1.0.1.dist-info/LICENSE
splink_data_generation-1.0.1.dist-info/WHEEL
splink_data_generation-1.0.1.dist-info/METADATA
splink_data_generation-1.0.1.dist-info/RECORD
