Metadata-Version: 2.1
Name: splink-data-generation
Version: 1.0.1
Summary: Generate synthetic data with a specified data generating process
Author: Robin Linacre
Author-email: robinlinacre@hotmail.com
Requires-Python: >=3.6,<4.0
Classifier: Programming Language :: Python :: 3
Classifier: Programming Language :: Python :: 3.6
Classifier: Programming Language :: Python :: 3.7
Classifier: Programming Language :: Python :: 3.8
Classifier: Programming Language :: Python :: 3.9
Requires-Dist: numpy (>=1.13.3,<2.0.0)
Requires-Dist: pandas (>=1.0.0,<2.0.0)
Requires-Dist: splink (>=1.0.0)
